MongoNorm-0.4.0.dist-info/DESCRIPTION.rst
MongoNorm-0.4.0.dist-info/METADATA
MongoNorm-0.4.0.dist-info/RECORD
MongoNorm-0.4.0.dist-info/WHEEL
MongoNorm-0.4.0.dist-info/metadata.json
MongoNorm-0.4.0.dist-info/top_level.txt
mongonorm/__init__.py
mongonorm/cursor.py
mongonorm/database.py
mongonorm/document.py
mongonorm/mongo_client.py
